{"cameraMode":{"drawMode":0,"name":"Shaded","section":"Shading Mode"},"sceneLighting":false,"audioPlay":false,"sceneViewState":{"m_AlwaysRefresh":false,"showFog":true,"showSkybox":false,"showFlares":true,"showImageEffects":true,"showParticleSystems":true,"showVisualEffectGraphs":true,"m_FxEnabled":true},"in2DMode":false,"pivot":{"x":-0.23222887516021729,"y":16.216842651367189,"z":0.5017314553260803},"rotation":{"x":0.04886472225189209,"y":0.928979754447937,"z":-0.13271233439445496,"w":0.34205085039138796},"size":0.2948528528213501,"orthographic":false}